exoscene/__init__.py
exoscene/image.py
exoscene/planet.py
exoscene/star.py
exoscene/data/bpgs/bpgs_1.fits
exoscene/data/bpgs/bpgs_10.fits
exoscene/data/bpgs/bpgs_100.fits
exoscene/data/bpgs/bpgs_101.fits
exoscene/data/bpgs/bpgs_102.fits
exoscene/data/bpgs/bpgs_103.fits
exoscene/data/bpgs/bpgs_104.fits
exoscene/data/bpgs/bpgs_105.fits
exoscene/data/bpgs/bpgs_106.fits
exoscene/data/bpgs/bpgs_107.fits
exoscene/data/bpgs/bpgs_108.fits
exoscene/data/bpgs/bpgs_109.fits
exoscene/data/bpgs/bpgs_11.fits
exoscene/data/bpgs/bpgs_110.fits
exoscene/data/bpgs/bpgs_111.fits
exoscene/data/bpgs/bpgs_112.fits
exoscene/data/bpgs/bpgs_113.fits
exoscene/data/bpgs/bpgs_114.fits
exoscene/data/bpgs/bpgs_115.fits
exoscene/data/bpgs/bpgs_116.fits
exoscene/data/bpgs/bpgs_117.fits
exoscene/data/bpgs/bpgs_118.fits
exoscene/data/bpgs/bpgs_119.fits
exoscene/data/bpgs/bpgs_12.fits
exoscene/data/bpgs/bpgs_120.fits
exoscene/data/bpgs/bpgs_121.fits
exoscene/data/bpgs/bpgs_122.fits
exoscene/data/bpgs/bpgs_123.fits
exoscene/data/bpgs/bpgs_124.fits
exoscene/data/bpgs/bpgs_125.fits
exoscene/data/bpgs/bpgs_126.fits
exoscene/data/bpgs/bpgs_127.fits
exoscene/data/bpgs/bpgs_128.fits
exoscene/data/bpgs/bpgs_129.fits
exoscene/data/bpgs/bpgs_13.fits
exoscene/data/bpgs/bpgs_130.fits
exoscene/data/bpgs/bpgs_131.fits
exoscene/data/bpgs/bpgs_132.fits
exoscene/data/bpgs/bpgs_133.fits
exoscene/data/bpgs/bpgs_134.fits
exoscene/data/bpgs/bpgs_135.fits
exoscene/data/bpgs/bpgs_136.fits
exoscene/data/bpgs/bpgs_137.fits
exoscene/data/bpgs/bpgs_138.fits
exoscene/data/bpgs/bpgs_139.fits
exoscene/data/bpgs/bpgs_14.fits
exoscene/data/bpgs/bpgs_140.fits
exoscene/data/bpgs/bpgs_141.fits
exoscene/data/bpgs/bpgs_142.fits
exoscene/data/bpgs/bpgs_143.fits
exoscene/data/bpgs/bpgs_144.fits
exoscene/data/bpgs/bpgs_145.fits
exoscene/data/bpgs/bpgs_146.fits
exoscene/data/bpgs/bpgs_147.fits
exoscene/data/bpgs/bpgs_148.fits
exoscene/data/bpgs/bpgs_149.fits
exoscene/data/bpgs/bpgs_15.fits
exoscene/data/bpgs/bpgs_150.fits
exoscene-1.2.dist-info/LICENSE.pdf
exoscene-1.2.dist-info/LICENSE.txt
exoscene-1.2.dist-info/METADATA
exoscene-1.2.dist-info/WHEEL
exoscene-1.2.dist-info/top_level.txt
exoscene-1.2.dist-info/RECORD
