Metadata-Version: 2.1
Name: exoscene
Version: 1.2
Summary: Library for simulating direct images of exoplanetary systems.
Home-page: https://github.com/nasa/exoscene
Author: Neil T. Zimmerman
Author-email: neil.t.zimmerman@nasa.gov
License: UNKNOWN
Platform: UNKNOWN
Classifier: Programming Language :: Python :: 3
Classifier: License :: OSI Approved
Requires-Python: >=3.6
Requires-Dist: astropy (>=4.0)
Requires-Dist: numpy
Requires-Dist: scipy
Requires-Dist: scikit-image
Requires-Dist: pandas
Requires-Dist: ipython
Requires-Dist: matplotlib
Requires-Dist: notebook
